CHANGES.rst
COPYING.txt
MANIFEST.in
README.rst
setup.py
python_yr.egg-info/PKG-INFO
python_yr.egg-info/SOURCES.txt
python_yr.egg-info/dependency_links.txt
python_yr.egg-info/requires.txt
python_yr.egg-info/top_level.txt
yr/__init__.py
yr/libyr.py
yr/utils.py
yr/examples/credit.py
yr/examples/dictionary.py
yr/examples/forecast.py
yr/examples/forecast_hour_by_hour.py
yr/examples/forecast_hour_by_hour_json.py
yr/examples/forecast_json.py
yr/examples/forecast_xyz.py
yr/examples/now.py
yr/examples/now_json.py
yr/examples/wuurrd.py
yr/examples/xml_source.py
yr/languages/en.json
yr/languages/nb.json
yr/languages/nn.json