Metadata-Version: 1.1
Name: python-yr
Version: 1.4.3
Summary: Get the forecast from the norwegian wheather service yr.no in python
Home-page: https://github.com/wckd/python-yr
Author: Hugo Shamrock
Author-email: hugo.shamrock@gmail.com
License: UNKNOWN
Platform: UNKNOWN
Classifier: Programming Language :: Python :: 3
Classifier: Programming Language :: Python
Classifier: License :: OSI Approved :: GNU General Public License v3 or later (GPLv3+)
Classifier: Operating System :: OS Independent
Classifier: Development Status :: 5 - Production/Stable
Classifier: Intended Audience :: Developers
Classifier: Topic :: Internet
